{
  "id": "rss-20260624-ec2",
  "title": "Fired by Google for creating the Google workspace CLI",
  "source_url": "https://twitter.com/JPoehnelt/status/2069482265953087602",
  "source": "rss",
  "summary": "A developer claims they were fired by Google for creating an unofficial CLI tool for Google Workspace. The Hacker News discussion explores the implications of building internal tools, corporate policies on side projects, and the balance between innovation and employment risk.",
  "tags": [
    "tool"
  ],
  "status": "draft",
  "score": 3,
  "created_at": "2026-06-24T10:41:51.691306Z",
  "updated_at": "2026-06-24T10:42:29.062780Z"
}