{
  "id": "rss-20260718-5ac",
  "title": "Pebble Mega Update – July 2026",
  "source_url": "https://repebble.com/blog/pebble-mega-update-july-2026",
  "source": "rss",
  "summary": "Pebble announces a major update for July 2026, likely featuring new AI/ML capabilities or platform improvements. The high engagement (264 points, 178 comments) suggests significant community interest in the release.",
  "tags": [
    "tool",
    "deployment"
  ],
  "status": "draft",
  "score": 5,
  "created_at": "2026-07-18T09:16:15.452253Z",
  "updated_at": "2026-07-18T09:16:43.049930Z"
}