{
  "id": "rss-20260516-592",
  "title": "U.S. DOJ demands Apple and Google unmask over 100k users of car-tinkering app",
  "source_url": "https://macdailynews.com/2026/05/15/u-s-doj-demands-apple-and-google-unmask-over-100000-users-of-popular-car-tinkering-app-in-emissions-crackdown/",
  "source": "rss",
  "summary": "The U.S. Department of Justice is demanding Apple and Google reveal the identities of over 100,000 users of a car-tinkering app, as part of an emissions crackdown. This raises significant privacy and legal questions about user data protection, platform responsibility, and government overreach in the context of automotive software modifications.",
  "tags": [
    "tool"
  ],
  "status": "draft",
  "score": 2,
  "created_at": "2026-05-16T09:23:21.265885Z",
  "updated_at": "2026-05-16T09:23:53.119630Z"
}