{
  "id": "rss-20260627-584",
  "title": "What does it mean to be a mathematician when AI does the math?",
  "source_url": "https://spectrum.ieee.org/ai-in-mathematics",
  "source": "rss",
  "summary": "This is a discussion link exploring the philosophical and practical implications of AI's ability to perform mathematical tasks, questioning the evolving role of human mathematicians in an era of increasingly capable AI systems.",
  "tags": [
    "research"
  ],
  "status": "draft",
  "score": 4,
  "created_at": "2026-06-27T09:57:13.410498Z",
  "updated_at": "2026-06-27T09:57:53.616833Z"
}